crypto_scan/__init__.py
crypto_scan/chain_finder.py
crypto_scan/coin_gecko.py
crypto_scan/coin_market_cap.py
crypto_scan/configs.py
crypto_scan/scan.py
crypto_scan/utils.py
crypto_scan-0.3.5.dist-info/METADATA
crypto_scan-0.3.5.dist-info/WHEEL
crypto_scan-0.3.5.dist-info/top_level.txt
crypto_scan-0.3.5.dist-info/RECORD
