Metadata-Version: 2.1
Name: crypto-scan
Version: 0.3.5
Summary: Python SDK for query crypto data from various API services.
Home-page: https://github.com/ENsu/crypto-scan
Author: Ian Su
Author-email: ian@ivcrypto.io
License: none
Platform: UNKNOWN
Requires-Dist: requests
Requires-Dist: web3
Requires-Dist: pandas
Requires-Dist: tenacity
Requires-Dist: swifter
